{
    "meta": {
        "status": 200
    },
    "data": {
        "kanji": "\"技\"",
        "strokes": 7,
        "main_meanings": [
            "skill",
            "art",
            "craft",
            "ability",
            "feat",
            "performance",
            "vocation",
            "arts"
        ],
        "main_readings": {
            "kun": [
                "わざ"
            ],
            "on": [
                "ギ"
            ]
        },
        "meta": {
            "education": {
                "grade": null,
                "jlpt": null,
                "newspaper_rank": null
            },
            "dictionary_idxs": {
                "579": "A Guide To Reading and Writing Japanese (Florence Sakade)",
                "673": "A Guide To Reading and Writing Japanese 3rd edition (Henshall, Seeley and De Groot)",
                "644": "A Guide To Remembering Japanese Characters (Kenneth G. Henshall)",
                "387": "A New Dictionary of Kanji Usage",
                "1853": "Classic Nelson (Andrew Nelson)",
                "463": "Essential Kanji (P.G. O’Neill)",
                "558": "Japanese Kanji Flashcards (Max Hodges and Tomoko Okazaki)",
                "381": "Japanese Names (P.G. O’Neill)",
                "871": "Kanji and Kana (Spahn and Hadamitzky)",
                "891": "Kanji and Kana, 2nd Edition (Spahn and Hadamitzky)",
                "369": "Kanji in Context (Nishiguchi and Kono)",
                "857": "Kodansha Compact Kanji Guide",
                "292": "Kodansha Kanji Dictionary (Jack Halpern)",
                "185": "Kodansha Kanji Learner’s Dictionary (Jack Halpern)",
                "221": "Kodansha Kanji Learner’s Dictionary, 2nd Edition (Jack Halpern)",
                "719": "Les Kanjis dans la tete (Yves Maniette)",
                "11855": "Morohashi",
                "248": "New Japanese English Character Dictionary (Jack Halpern)",
                "2092": "New Nelson (John Haig)",
                "712": "Remembering The Kanji (James Heisig)",
                "769": "Remembering The Kanji, 6th edition (James Heisig)",
                "665": "Tuttle Kanji Cards (Alexander Kask)"
            },
            "classifications": {
                "1367": "2001 Kanji",
                "3c4.16": "The Kanji Dictionary",
                "1-3-4": "SKIP code",
                "5404.7": "Four corner code"
            },
            "codepoints": {
                "1-21-27": "JIS X 0208-1997 kuten code",
                "6280": "Unicode hex code"
            },
            "readings": {
                "japanese": null,
                "chinese": [
                    "ji4"
                ],
                "korean": [
                    "gi"
                ]
            }
        },
        "radical": {
            "alt_forms": [
                "扌龵"
            ],
            "meaning": "hand",
            "parts": [
                "十",
                "又",
                "扎",
                "支"
            ],
            "basis": "手",
            "kangxi_order": 64,
            "variants": null
        },
        "reading_examples": {
            "kun": [
                {
                    "kanji": "技",
                    "reading": "わざ",
                    "meanings": [
                        "technique",
                        "art",
                        "skill",
                        "move"
                    ]
                },
                {
                    "kanji": "技あり",
                    "reading": "わざあり",
                    "meanings": [
                        "waza-ari (in judo",
                        "a half-point awarded for good but incomplete execution)"
                    ]
                },
                {
                    "kanji": "寝技",
                    "reading": "ねわざ",
                    "meanings": [
                        "pinning technique (in wrestling or judo)",
                        "underhanded dealings"
                    ]
                },
                {
                    "kanji": "投げ技",
                    "reading": "なげわざ",
                    "meanings": [
                        "throw or throwing technique (sumo",
                        "judo)"
                    ]
                }
            ],
            "on": [
                {
                    "kanji": "技",
                    "reading": "ワザ",
                    "meanings": [
                        "technique",
                        "art",
                        "skill",
                        "move"
                    ]
                },
                {
                    "kanji": "技巧",
                    "reading": "ギコウ",
                    "meanings": [
                        "technique",
                        "finesse"
                    ]
                },
                {
                    "kanji": "国技",
                    "reading": "コクギ",
                    "meanings": [
                        "national sport (e.g. sumo)"
                    ]
                },
                {
                    "kanji": "陸上競技",
                    "reading": "リクジョウキョウギ",
                    "meanings": [
                        "track-and-field events"
                    ]
                }
            ]
        }
    }
}