{
    "meta": {
        "status": 200
    },
    "data": {
        "kanji": "\"槻\"",
        "strokes": 15,
        "main_meanings": [
            "Zelkova tree"
        ],
        "main_readings": {
            "kun": [
                "つき"
            ],
            "on": [
                "キ"
            ]
        },
        "meta": {
            "education": {
                "grade": null,
                "jlpt": null,
                "newspaper_rank": null
            },
            "dictionary_idxs": {
                "2352": "Classic Nelson (Andrew Nelson)",
                "2295": "Japanese Names (P.G. O’Neill)",
                "2126": "Kanji and Kana (Spahn and Hadamitzky)",
                "1349": "Kodansha Kanji Dictionary (Jack Halpern)",
                "732": "Kodansha Kanji Learner’s Dictionary (Jack Halpern)",
                "978": "Kodansha Kanji Learner’s Dictionary, 2nd Edition (Jack Halpern)",
                "15390": "Morohashi",
                "2845": "New Nelson (John Haig)",
                "2527": "Remembering The Kanji (James Heisig)",
                "2587": "Remembering The Kanji, 6th edition (James Heisig)"
            },
            "classifications": {
                "4a11.4": "The Kanji Dictionary",
                "1-4-11": "SKIP code",
                "4691.0": "Four corner code"
            },
            "codepoints": {
                "1-36-48": "JIS X 0208-1997 kuten code",
                "69fb": "Unicode hex code"
            },
            "readings": {
                "japanese": null,
                "chinese": [
                    "gui1"
                ],
                "korean": [
                    "gyu"
                ]
            }
        },
        "radical": {
            "alt_forms": null,
            "meaning": "tree",
            "parts": [
                "一",
                "二",
                "人",
                "大",
                "木",
                "見"
            ],
            "basis": "木",
            "kangxi_order": 75,
            "variants": null
        },
        "reading_examples": {
            "kun": null,
            "on": [
                {
                    "kanji": "欅",
                    "reading": "けやき",
                    "meanings": [
                        "Japanese zelkova (Zelkova serrata)"
                    ]
                },
                {
                    "kanji": "槻欅",
                    "reading": "つきげやき",
                    "meanings": [
                        "Japanese zelkova (Zelkova serrata)"
                    ]
                }
            ]
        }
    }
}